setup.py
loremipsum/__init__.py
loremipsum/action.py
py_lorem.egg-info/PKG-INFO
py_lorem.egg-info/SOURCES.txt
py_lorem.egg-info/dependency_links.txt
py_lorem.egg-info/not-zip-safe
py_lorem.egg-info/top_level.txt