Metadata-Version: 1.0
Name: py-lorem
Version: 1.1
Summary: Generate mock sentences/paragraphs with the Lorem Ipsum prose
Home-page: https://github.com/nubela/py-lorem
Author: nubela
Author-email: nubela@gmail.com
License: MIT
Platform: UNKNOWN
